rezbuild/__init__.py
rezbuild/bin_utils.py
rezbuild/builder.py
rezbuild/constants.py
rezbuild/exceptions.py
rezbuild/log.py
rezbuild/utils.py
rezbuild-0.16.0.dist-info/LICENSE
rezbuild-0.16.0.dist-info/METADATA
rezbuild-0.16.0.dist-info/WHEEL
rezbuild-0.16.0.dist-info/top_level.txt
rezbuild-0.16.0.dist-info/RECORD
