Metadata-Version: 2.1
Name: rezbuild
Version: 0.16.0
Summary: Build rez packages.
Home-page: https://gitlab.com/Pili-Pala/rezbuild
Author: PiliPala
Author-email: pypi@pilipala.io
License: GPLv3
Project-URL: Bug Tracker, https://gitlab.com/Pili-Pala/rezbuild/issues
Keywords: rez,build
Classifier: Development Status :: 4 - Beta
Classifier: Intended Audience :: Developers
Classifier: License :: OSI Approved :: GNU General Public License v3 (GPLv3)
Classifier: Natural Language :: English
Classifier: Operating System :: OS Independent
Classifier: Programming Language :: Python :: 3
Classifier: Programming Language :: Python :: 3.6
Classifier: Programming Language :: Python :: 3.7
Classifier: Programming Language :: Python :: 3.8
Classifier: Programming Language :: Python :: 3.9
Classifier: Programming Language :: Python :: 3.10
Classifier: Topic :: Games/Entertainment
Classifier: Topic :: Software Development :: Build Tools
Requires-Python: <4,>=3.6
License-File: LICENSE
Requires-Dist: pip >=18.0
Requires-Dist: build >=0.3
